Metadata-Version: 2.1
Name: django-stack-it
Version: 0.1.18
Summary: Content management system: Pages is a list of (ordered) block and relevant content. Though to allow inline i18n content management, with high performance usage.
Home-page: https://github.com/jufik/django_stack_it
Author: Julien Kieffer
Author-email: julien@vingtcinq.io
License: MIT
Keywords: django_stack_it
Platform: UNKNOWN
Classifier: Development Status :: 3 - Alpha
Classifier: Framework :: Django :: 2.1
Classifier: Intended Audience :: Developers
Classifier: License :: OSI Approved :: BSD License
Classifier: Natural Language :: English
Classifier: Programming Language :: Python :: 3.6
Requires-Dist: Django (>=2.1)
Requires-Dist: django-imagekit
Requires-Dist: pillow
Requires-Dist: django-model-utils
Requires-Dist: django-mptt
Requires-Dist: django-polymorphic
Requires-Dist: django-polymorphic-tree
